aneuploidy/__init__.py
aneuploidy/actions.py
aneuploidy/assign.py
aneuploidy/chromosome.py
aneuploidy/clustering.py
aneuploidy/colormaps.py
aneuploidy/colors.py
aneuploidy/constants.py
aneuploidy/corrections.py
aneuploidy/data.py
aneuploidy/filters.py
aneuploidy/idmap.py
aneuploidy/index.py
aneuploidy/io_.py
aneuploidy/json.py
aneuploidy/parameters.py
aneuploidy/pipelines.py
aneuploidy/segments.py
aneuploidy/style.mplstyle
aneuploidy/test_helpers.py
aneuploidy/testing.py
aneuploidy/utils.py
aneuploidy/changepoints/__init__.py
aneuploidy/changepoints/changepoints.py
aneuploidy/changepoints/rpt.py
aneuploidy/changepoints/sdt.py
aneuploidy/entrypoints/__init__.py
aneuploidy/entrypoints/cli.py
aneuploidy/entrypoints/debug_export.py
aneuploidy/entrypoints/detail_plot.py
aneuploidy/entrypoints/export.py
aneuploidy/entrypoints/plot.py
aneuploidy/plots/__init__.py
aneuploidy/plots/binarized_correlations.py
aneuploidy/plots/copy_number.py
aneuploidy/plots/histograms.py
aneuploidy/plots/matrix.py
aneuploidy/plots/plotmanager.py
aneuploidy/pyarmor_runtime_000000/__init__.py
aneuploidy/pyarmor_runtime_000000/pyarmor_runtime.so
aneuploidy-0.24.0.5.dist-info/LICENSE
aneuploidy-0.24.0.5.dist-info/METADATA
aneuploidy-0.24.0.5.dist-info/WHEEL
aneuploidy-0.24.0.5.dist-info/entry_points.txt
aneuploidy-0.24.0.5.dist-info/top_level.txt
aneuploidy-0.24.0.5.dist-info/RECORD
