Metadata-Version: 2.1
Name: aneuploidy
Version: 0.24.0.5
Summary: Detect aneuploidies in copy number data
License: AGPLv3
Platform: linux
License-File: LICENSE
